pybammeis/__init__.py
pybammeis/eis_simulation.py
pybammeis/numerical_methods.py
pybammeis/plotting.py
pybammeis/utils.py
pybammeis/version.py
pybammeis-0.1.5.dist-info/LICENSE.md
pybammeis-0.1.5.dist-info/METADATA
pybammeis-0.1.5.dist-info/WHEEL
pybammeis-0.1.5.dist-info/top_level.txt
pybammeis-0.1.5.dist-info/RECORD
