Metadata-Version: 2.1
Name: pybammeis
Version: 0.1.5
Summary: PyBaMM EIS
License: Copyright © 2022-2024 University of Oxford
Requires-Python: >=3.10
License-File: LICENSE.md
Requires-Dist: pybamm[all]>=24.9
Requires-Dist: matplotlib
Provides-Extra: dev
Requires-Dist: pytest; extra == "dev"
Requires-Dist: sphinx; extra == "dev"
Requires-Dist: myst-parser; extra == "dev"
Requires-Dist: nbmake; extra == "dev"
Requires-Dist: pytest-html; extra == "dev"
Requires-Dist: pytest-cov; extra == "dev"
Provides-Extra: docs
Requires-Dist: autodoc; extra == "docs"
Requires-Dist: mathjax; extra == "docs"
Requires-Dist: myst-parser; extra == "docs"
